cli_plot/__init__.py
cli_plot/config.py
cli_plot/functions.py
cli_plot/mouse_event_handlers.py
cli_plot/plot.py
cli_plot/series.py
cli_plot/util.py
cli_plot-1.1.2.dist-info/LICENSE
cli_plot-1.1.2.dist-info/METADATA
cli_plot-1.1.2.dist-info/WHEEL
cli_plot-1.1.2.dist-info/dependency_links.txt
cli_plot-1.1.2.dist-info/entry_points.txt
cli_plot-1.1.2.dist-info/top_level.txt
cli_plot-1.1.2.dist-info/RECORD
