Metadata-Version: 2.1
Name: cli-plot
Version: 1.1.2
Summary: A commandline app for plotting datafiles
Home-page: https://github.com/John-Lee-Cooper/cli_plot
Download-URL: https://github.com/John-Lee-Cooper/cli_plot/archive/1.0.0.tar.gz
Author: John Lee Cooper
Author-email: cooperjl90@gmail.com
License: MIT
Classifier: License :: OSI Approved :: MIT License
Classifier: Programming Language :: Python :: 3
Classifier: Programming Language :: Python :: 3.7
Requires-Python: >=3.6
License-File: LICENSE
Requires-Dist: click (==8.1.3)
Requires-Dist: cycler (==0.11.0)
Requires-Dist: kiwisolver (==1.4.2)
Requires-Dist: matplotlib (==3.4.3)
Requires-Dist: numpy (==1.22.4)
Requires-Dist: pandas (==1.4.2)
Requires-Dist: pep517 (==0.12.0)
Requires-Dist: Pillow (==9.1.1)
Requires-Dist: pip-tools (==6.6.2)
Requires-Dist: pyparsing (==3.0.9)
Requires-Dist: python-dateutil (==2.8.2)
Requires-Dist: pytz (==2022.1)
Requires-Dist: scipy (==1.8.1)
Requires-Dist: seaborn (==0.11.2)
Requires-Dist: six (==1.16.0)
Requires-Dist: tomli (==2.0.1)
Requires-Dist: typer (==0.4.1)
